{"tokens": {"rrpair::per_ketua::abdul-majid": {"idx": 1, "meta": {"ketua": "Dr. H. Abdul Majid, S.HI., M.H.", "combos_len": 4, "last_used_combo": {"pp": "Runie Handayani, S.H., M.H.", "js": "Sri Maryati, A.Md"}}}, "rrpair::per_ketua::mulathifah": {"idx": 2, "meta": {"ketua": "Dra. Mulathifah, M.H.", "combos_len": 4, "last_used_combo": {"pp": "Nur Holia, S.H., M.H.", "js": "Rina Marlina, SE"}}, "updated_at": "2025-09-02T15:35:07.256986"}, "rrpair::per_ketua::taslimah": {"idx": 3, "meta": {"ketua": "Dra. Taslimah, M.H", "combos_len": 4, "last_used_combo": {"pp": "Muhammad Thahir Guhir, S.H.,M.H.", "js": "nama"}}, "updated_at": "2025-09-02T15:55:49.586918"}, "rrpair::per_ketua::agus-abdullah": {"idx": 2, "meta": {"ketua": "Drs. Agus Abdullah, M.H.", "combos_len": 4, "last_used_combo": {"pp": "Neneng Kurniati, S.Ag.", "js": "Monika Septi Indriyani, A.Md."}}, "updated_at": "2025-09-02T15:35:34.886986"}, "rrpair::per_ketua::syakhrani": {"idx": 2, "meta": {"ketua": "Drs. H. Syakhrani", "combos_len": 4, "last_used_combo": {"pp": "Muhammad Syaifur Rohim, S.E.I.", "js": "Khairunas, S.H.I."}}, "updated_at": "2025-09-02T15:48:40.069092"}, "rrpair::per_ketua::ifdal": {"idx": 2, "meta": {"ketua": "Drs. Ifdal, S.H.", "combos_len": 4, "last_used_combo": {"pp": "Zamzam Lubis, S.H., M.H.", "js": "Zainal Arifin"}}, "updated_at": "2025-09-02T15:36:29.316610"}, "rrpair::per_ketua::jajat-sudrajat": {"idx": 2, "meta": {"ketua": "Drs. Jajat Sudrajat, S.H., M.H", "combos_len": 4, "last_used_combo": {"pp": "Widya Fausiah, S.E., M.H.", "js": "Aji Djuanda Rachmad"}}, "updated_at": "2025-09-02T15:49:19.715084"}, "rrpair::per_ketua::sohel": {"idx": 2, "meta": {"ketua": "Drs. Sohel, S.H.", "combos_len": 4, "last_used_combo": {"pp": "Sirajuddin Haris, S.H.", "js": "Umi Nurulia"}}, "updated_at": "2025-09-02T16:00:19.723106"}, "rrpair::per_ketua::idawati-ag": {"idx": 2, "meta": {"ketua": "Idawati, S.Ag.,M.H.", "combos_len": 4, "last_used_combo": {"pp": "Andar Aryani, S.H.,M.H.", "js": "nama"}}, "updated_at": "2025-09-02T15:54:59.447382"}, "rrpair::per_ketua::zaenal-murhofa": {"idx": 2, "meta": {"ketua": "Drs. Zaenal Murhofa, S.H.. M.H", "combos_len": 4, "last_used_combo": {"pp": "Hj. Alfiah Yuliastuti, S.H., M.H", "js": "Sanjaya Langgeng Santoso"}}, "updated_at": "2025-09-02T15:49:58.678082"}, "rrpair::per_ketua::suryadi-ag": {"idx": 1, "meta": {"ketua": "Suryadi, S.Ag., S.H., M.H.", "combos_len": 4, "last_used_combo": {"pp": "Muhammad Iqbal, S.Ag., S.H., M.H.", "js": "Irvan Riditya Fauzi, A.Md"}}, "updated_at": "2025-09-02T15:34:09.459204"}}, "pending": {}}